farc/Ahsm.py
farc/Event.py
farc/Framework.py
farc/Hsm.py
farc/Signal.py
farc/Spy.py
farc/TimeEvent.py
farc/VcdSpy.py
farc/__init__.py
farc-0.1.1.dist-info/LICENSE
farc-0.1.1.dist-info/METADATA
farc-0.1.1.dist-info/WHEEL
farc-0.1.1.dist-info/top_level.txt
farc-0.1.1.dist-info/RECORD
