Metadata-Version: 2.1
Name: farc
Version: 0.1.1
Summary: Framework for Asyncio/Actor/AHSM Run-to-completion Concurrency
Home-page: https://github.com/dwhall/farc
Author: Dean Hall
Author-email: dwhall256@gmail.com
License: UNKNOWN
Platform: UNKNOWN
Classifier: License :: OSI Approved :: MIT License
Classifier: Operating System :: OS Independent
Classifier: Topic :: Software Development :: Libraries :: Application Frameworks
Classifier: Intended Audience :: Developers
Classifier: Development Status :: 3 - Alpha
Classifier: Programming Language :: Python :: 3.4
Classifier: Programming Language :: Python :: 3.5
Classifier: Programming Language :: Python :: 3.6
Classifier: Programming Language :: Python :: 3.7
Classifier: Programming Language :: Python :: 3.8
